Workbook

Sheet SQL Statistics
A1: sql 文件名 | B1: 数仓表 | C1: 通过 Trae 得到的结果 | F1: 通过执行数仓表得到的结果 | G1: 直接查 SQL 得到的数据条数 | H1: 是否一致
A2: active_review_rates_city_monthly_yoy.sql | B2: =VLOOKUP(A2,[1]SQL脚本清单!$B:$C,2,0) -> ads_mgt_report_turnover_active_review_rates_city_monthly_yoy | C2: 135 | E2: ads_mgt_report_cashflow_cash_flow_closing_warning | F2: 0 | G2: =VLOOKUP(E2,B:C,2,0) -> 0 | H2: =G2=F2 -> TRUE
A3: active_review_rates_monthly_yoy.sql | B3: =VLOOKUP(A3,[1]SQL脚本清单!$B:$C,2,0) -> ads_mgt_report_turnover_active_review_rates_monthly_yoy | C3: 14 | E3: ads_mgt_report_cashflow_cash_flow_continuous_loss | F3: 0 | G3: =VLOOKUP(E3,B:C,2,0) -> 0 | H3: =G3=F3 -> TRUE
A4: active_review_rates_store_monthly_yoy.sql | B4: =VLOOKUP(A4,[1]SQL脚本清单!$B:$C,2,0) -> ads_mgt_report_turnover_active_review_rates_store_monthly_yoy | C4: 3534 | E4: ads_mgt_report_turnover_member_churn_rate_monthly_yoy | F4: 14 | G4: =VLOOKUP(E4,B:C,2,0) -> 14 | H4: =G4=F4 -> TRUE
A5: active_user_city_monthly_yoy.sql | B5: =VLOOKUP(A5,[1]SQL脚本清单!$B:$C,2,0) -> ads_mgt_report_turnover_active_user_city_monthly_yoy | C5: 126 | E5: ads_mgt_report_turnover_staff_avg_svc_dur_m_yoy | F5: 14 | G5: =VLOOKUP(E5,B:C,2,0) -> 14 | H5: =G5=F5 -> TRUE
A6: active_user_monthly_yoy.sql | B6: =VLOOKUP(A6,[1]SQL脚本清单!$B:$C,2,0) -> ads_mgt_report_turnover_active_user_monthly_yoy | C6: 14 | E6: ads_mgt_report_turnover_staff_avg_svc_dur_store_m_yoy | F6: 2620 | G6: =VLOOKUP(E6,B:C,2,0) -> 2762 | H6: =G6=F6 -> FALSE
A7: active_user_store_monthly_yoy.sql | B7: =VLOOKUP(A7,[1]SQL脚本清单!$B:$C,2,0) -> ads_mgt_report_turnover_active_user_store_monthly_yoy | C7: 2621 | E7: ads_mgt_report_turnover_staff_svc_dur_below_std_m | F7: 14 | G7: =VLOOKUP(E7,B:C,2,0) -> 14 | H7: =G7=F7 -> TRUE
A8: avg_order_value_annual_yoy.sql | B8: =VLOOKUP(A8,[1]SQL脚本清单!$B:$C,2,0) -> ads_mgt_report_turnover_avg_order_value_annual_yoy | C8: 4 | E8: ads_mgt_report_turnover_turnover_weekly_avg_per_day_yoy | F8: 58 | G8: =VLOOKUP(E8,B:C,2,0) -> 58 | H8: =G8=F8 -> TRUE
A9: avg_order_value_city_annual_yoy.sql | B9: =VLOOKUP(A9,[1]SQL脚本清单!$B:$C,2,0) -> ads_mgt_report_turnover_avg_order_value_city_annual_yoy | C9: 38 | E9: ads_mgt_report_turnover_turnover_weekly_cum_yoy | F9: 58 | G9: =VLOOKUP(E9,B:C,2,0) -> 58 | H9: =G9=F9 -> TRUE
A10: avg_order_value_city_weekly_ytd_yoy.sql | B10: =VLOOKUP(A10,[1]SQL脚本清单!$B:$C,2,0) -> ads_mgt_report_turnover_avg_order_value_city_weekly_ytd_yoy | C10: 561 | E10: ads_mgt_report_turnover_turnover_weekly | F10: 58 | G10: =VLOOKUP(E10,B:C,2,0) -> 58 | H10: =G10=F10 -> TRUE
A11: avg_order_value_store_weekly_ytd_yoy.sql | B11: =VLOOKUP(A11,[1]SQL脚本清单!$B:$C,2,0) -> ads_mgt_report_turnover_avg_order_value_store_weekly_ytd_yoy | C11: 20059 | E11: ads_mgt_report_turnover_avg_order_value_weekly_ytd_yoy | F11: 58 | G11: =VLOOKUP(E11,B:C,2,0) -> 58 | H11: =G11=F11 -> TRUE
A12: avg_order_value_weekly_yoy.sql | B12: =VLOOKUP(A12,[1]SQL脚本清单!$B:$C,2,0) -> ads_mgt_report_turnover_avg_order_value_weekly_yoy | C12: 58 | E12: ads_mgt_report_turnover_bed_to_staff_ratio_city_annual | F12: 18 | G12: =VLOOKUP(E12,B:C,2,0) -> 18 | H12: =G12=F12 -> TRUE
A13: avg_order_value_weekly_ytd_yoy.sql | B13: =VLOOKUP(A13,[1]SQL脚本清单!$B:$C,2,0) -> ads_mgt_report_turnover_avg_order_value_weekly_ytd_yoy | C13: 58 | E13: ads_mgt_report_cf_new_store_op | F13: 20 | G13: =VLOOKUP(E13,B:C,2,0) -> 20 | H13: =G13=F13 -> TRUE
... A62: user_visit_count_daily_avg_visit_monthly.sql | B62: =VLOOKUP(A62,[1]SQL脚本清单!$B:$C,2,0) -> ads_mgt_report_turnover_user_visit_count_daily_avg_visit_monthly | C62: 14 | E62: ads_mgt_report_turnover_staff_avg_svc_dur_city_m_yoy | F62: 126 | G62: =VLOOKUP(E62,B:C,2,0) -> 126 | H62: =G62=F62 -> TRUE
